no_more_qs/__init__.py
no_more_query_string-0.0.8.dist-info/LICENSE
no_more_query_string-0.0.8.dist-info/METADATA
no_more_query_string-0.0.8.dist-info/WHEEL
no_more_query_string-0.0.8.dist-info/top_level.txt
no_more_query_string-0.0.8.dist-info/RECORD
