Metadata-Version: 2.1
Name: no-more-query-string
Version: 0.0.8
Summary: Remove unneccessary query-string from the URL given. Especially fbclid.
Home-page: https://github.com/EltonChou/no-more-query-string
Author: Elton H.Y. Chou
Author-email: plscd748@gmail.com
License: MIT
Project-URL: Bug Tracker, https://github.com/EltonChou/no-more-query-string/issues
Project-URL: Source Code, https://github.com/EltonChou/no-more-query-string/
Project-URL: Changelog, https://github.com/EltonChou/no-more-query-string/blob/main/CHANGELOG.md
Keywords: fbclid,query strings,python
Platform: UNKNOWN
Classifier: Development Status :: 4 - Beta
Classifier: Programming Language :: Python :: 3.6
Classifier: Programming Language :: Python :: 3.7
Classifier: Programming Language :: Python :: 3.8
Classifier: Programming Language :: Python :: 3.9
Classifier: Environment :: Web Environment
Classifier: Intended Audience :: Developers
Classifier: Operating System :: OS Independent
Classifier: Topic :: Internet
Classifier: Topic :: Software Development :: Libraries :: Python Modules
Classifier: License :: OSI Approved :: MIT License
Requires-Python: >=3.6, <4
Requires-Dist: requests
Requires-Dist: beautifulsoup4
Requires-Dist: lxml
Requires-Dist: tld
Requires-Dist: w3lib
